{
  "Version": "2012-10-17",
  "Statement": [
    {
      "Effect": "Allow",
      "Resource": "*",
      "Action": [
        "ec2:Describe*",
        "cloudwatch:PutMetricAlarm",
        "cloudwatch:DeleteAlarms",
        "cloudwatch:*",
        "ecs:Describe*",
        "logs:Create*",
        "logs:PutLogEvents",
        "logs:DescribeLogGroups",
        "ecr:BatchCheckLayerAvailability",
        "ecr:BatchGetImage",
        "ecr:DescribeImages",
        "ecr:DescribeRepositories",
        "ecr:GetAuthorizationToken",
        "ecr:GetDownloadUrlForLayer",
        "ecr:GetRepositoryPolicy",
        "ecr:ListImages",
        "s3:*",
        "ecs:Poll",
        "ecs:StartTelemetrySession"
      ]
    }
  ]
}